MANIFEST.in
requirements.txt
setup.py
taskwarrior_pomodoro_beeminder/__init__.py
taskwarrior_pomodoro_beeminder/beeminder.py
taskwarrior_pomodoro_beeminder/cmdline.py
taskwarrior_pomodoro_beeminder/commands.py
taskwarrior_pomodoro_beeminder/config.py
taskwarrior_pomodoro_beeminder/utils.py
taskwarrior_pomodoro_beeminder.egg-info/PKG-INFO
taskwarrior_pomodoro_beeminder.egg-info/SOURCES.txt
taskwarrior_pomodoro_beeminder.egg-info/dependency_links.txt
taskwarrior_pomodoro_beeminder.egg-info/entry_points.txt
taskwarrior_pomodoro_beeminder.egg-info/requires.txt
taskwarrior_pomodoro_beeminder.egg-info/top_level.txt