Metadata-Version: 1.1
Name: taskwarrior-pomodoro-beeminder
Version: 0.2.0
Summary: Increment Beeminder task every time you complete a pomodoro.
Home-page: https://github.com/coddingtonbear/taskwarrior-pomodoro-beeminder
Author: Adam Coddington
Author-email: me@adamcoddington.net
License: UNKNOWN
Platform: UNKNOWN
Classifier: License :: OSI Approved :: MIT License
Classifier: Operating System :: OS Independent
Classifier: Programming Language :: Python :: 3
